axiomtradeapi/__init__.py
axiomtradeapi/_client.py
axiomtradeapi/_client_fixed.py
axiomtradeapi/client.py
axiomtradeapi/urls.py
axiomtradeapi/__pycache__/__init__.cpython-312.pyc
axiomtradeapi/__pycache__/__init__.cpython-313.pyc
axiomtradeapi/__pycache__/_client.cpython-312.pyc
axiomtradeapi/__pycache__/_client.cpython-313.pyc
axiomtradeapi/__pycache__/client.cpython-312.pyc
axiomtradeapi/__pycache__/urls.cpython-312.pyc
axiomtradeapi/auth/__init__.py
axiomtradeapi/auth/auth_manager.py
axiomtradeapi/auth/login.py
axiomtradeapi/auth/__pycache__/__init__.cpython-312.pyc
axiomtradeapi/auth/__pycache__/auth_manager.cpython-312.pyc
axiomtradeapi/auth/__pycache__/login.cpython-312.pyc
axiomtradeapi/content/__init__.py
axiomtradeapi/content/endpoints.py
axiomtradeapi/content/__pycache__/__init__.cpython-312.pyc
axiomtradeapi/content/__pycache__/__init__.cpython-313.pyc
axiomtradeapi/content/__pycache__/endpoints.cpython-312.pyc
axiomtradeapi/content/__pycache__/endpoints.cpython-313.pyc
axiomtradeapi/helpers/TryServers.py
axiomtradeapi/helpers/_init__.py
axiomtradeapi/helpers/help.py
axiomtradeapi/helpers/trending_tokens.py
axiomtradeapi/helpers/__pycache__/TryServers.cpython-312.pyc
axiomtradeapi/helpers/__pycache__/help.cpython-312.pyc
axiomtradeapi/helpers/__pycache__/help.cpython-313.pyc
axiomtradeapi/websocket/_client.py
axiomtradeapi/websocket/__pycache__/_client.cpython-312.pyc
axiomtradeapi/websocket/__pycache__/_client.cpython-313.pyc
axiomtradeapi-1.0.4.dist-info/licenses/LICENSE
axiomtradeapi-1.0.4.dist-info/METADATA
axiomtradeapi-1.0.4.dist-info/WHEEL
axiomtradeapi-1.0.4.dist-info/top_level.txt
axiomtradeapi-1.0.4.dist-info/RECORD
