Metadata-Version: 2.4
Name: axiomtradeapi
Version: 1.0.4
Summary: A comprehensive Python client for the AxiomTrade API with automatic token management, secure authentication, and extensive trading analytics for Solana meme tokens.
Home-page: https://github.com/ChipaDevTeam/AxiomTradeAPI-py
Author: ChipaDevTeam
Author-email: 
License: MIT
Project-URL: Homepage, https://github.com/ChipaDevTeam/AxiomTradeAPI-py
Project-URL: Repository, https://github.com/ChipaDevTeam/AxiomTradeAPI-py
Project-URL: Documentation, https://chipadevteam.github.io/AxiomTradeAPI-py/
Project-URL: Bug Reports, https://github.com/ChipaDevTeam/AxiomTradeAPI-py/issues
Keywords: axiom,trade,solana,crypto,trading,api,websocket,telegram,bot,meme,tokens,analytics,authentication
Classifier: Development Status :: 5 - Production/Stable
Classifier: Intended Audience :: Developers
Classifier: Topic :: Software Development :: Libraries :: Python Modules
Classifier: Topic :: Office/Business :: Financial :: Investment
Classifier: License :: OSI Approved :: MIT License
Classifier: Programming Language :: Python :: 3
Classifier: Programming Language :: Python :: 3.7
Classifier: Programming Language :: Python :: 3.8
Classifier: Programming Language :: Python :: 3.9
Classifier: Programming Language :: Python :: 3.10
Classifier: Programming Language :: Python :: 3.11
Classifier: Programming Language :: Python :: 3.12
Classifier: Operating System :: OS Independent
Requires-Python: >=3.7
License-File: LICENSE
Requires-Dist: websockets>=10.0
Requires-Dist: python-dotenv
Requires-Dist: solders
Requires-Dist: requests>=2.25.1
Requires-Dist: base58>=2.1.0
Requires-Dist: cryptography>=3.4.8
Provides-Extra: telegram
Requires-Dist: python-telegram-bot>=20.0; extra == "telegram"
Provides-Extra: dev
Requires-Dist: pytest; extra == "dev"
Requires-Dist: black; extra == "dev"
Requires-Dist: flake8; extra == "dev"
Dynamic: home-page
Dynamic: license-file
Dynamic: requires-python
